qt_parameters/__init__.py
qt_parameters/box.py
qt_parameters/editor.py
qt_parameters/inputs.py
qt_parameters/list.py
qt_parameters/rediotab.py
qt_parameters/resizegrip.py
qt_parameters/scrollarea.py
qt_parameters/tabdata.py
qt_parameters/utils.py
qt_parameters/widgets.py
qt_parameters-1.3.0.dist-info/licenses/LICENSE
qt_parameters-1.3.0.dist-info/METADATA
qt_parameters-1.3.0.dist-info/WHEEL
qt_parameters-1.3.0.dist-info/top_level.txt
qt_parameters-1.3.0.dist-info/RECORD
