Metadata-Version: 2.4
Name: qt-parameters
Version: 1.3.0
Summary: Qt parameter widgets and forms for Python.
Author: Beat Reichenbach
License: MIT
Requires-Python: >=3.9
License-File: LICENSE
Requires-Dist: qtpy<3,>=2.0
Requires-Dist: qt-material-icons<1,>=0.2
Provides-Extra: dev
Requires-Dist: black>=24.0; extra == "dev"
Requires-Dist: python-semantic-release>=9.0; extra == "dev"
Requires-Dist: qt-themes>=0.2; extra == "dev"
Requires-Dist: PySide6; extra == "dev"
Provides-Extra: pyside2
Requires-Dist: PySide2; extra == "pyside2"
Provides-Extra: pyside6
Requires-Dist: PySide6; extra == "pyside6"
Dynamic: license-file
